{
  "fetched_at": "2026-05-06T12:28:06.156858Z",
  "source": "Grayson County TX \u2013 PublicSearch",
  "date_range": {
    "from": "04/29/2026",
    "to": "05/06/2026"
  },
  "total": 19,
  "with_address": 19,
  "records": [
    {
      "doc_num": "2026-10607",
      "doc_type": "AH",
      "filed": "2026-04-29",
      "cat": "probate",
      "cat_label": "Affidavit of Heirship",
      "owner": "GARVIN BARBARA NELL",
      "grantee": "SANDS DOROTHY JOAN DECEASED",
      "amount": null,
      "legal": "Survey - Name: DC SHELP SUR Survey: 1097 Acres: 3.004",
      "prop_address": "OFF JOHNSON RD",
      "prop_city": "Sherman",
      "prop_state": "TX",
      "prop_zip": "",
      "mail_address": "334 JOHNSON RD",
      "mail_city": "DENISON",
      "mail_state": "TX",
      "mail_zip": "75021",
      "clerk_url": "https://grayson.tx.publicsearch.us/results?department=RP&_docTypes=AH&recordedDateRange=20260429,20260506&searchType=quickSearch&keywordSearch=false&searchOcrText=false",
      "flags": [
        "Probate / estate",
        "New this week"
      ],
      "score": 70,
      "_demo": false
    },
    {
      "doc_num": "2026-10785",
      "doc_type": "PB",
      "filed": "2026-04-30",
      "cat": "probate",
      "cat_label": "Probate",
      "owner": "GRESHAM ARNOLD EDGAR DECEASED ESTATE",
      "grantee": "PUBLIC",
      "amount": null,
      "legal": "N/A",
      "prop_address": "207 PARADISE PARK RD",
      "prop_city": "POTTSBORO",
      "prop_state": "TX",
      "prop_zip": "",
      "mail_address": "1642 SPEEDWAY AVE",
      "mail_city": "WICHITA FALLS",
      "mail_state": "TX",
      "mail_zip": "76301",
      "clerk_url": "https://grayson.tx.publicsearch.us/results?department=RP&_docTypes=PB&recordedDateRange=20260429,20260506&searchType=quickSearch&keywordSearch=false&searchOcrText=false",
      "flags": [
        "Probate / estate",
        "New this week"
      ],
      "score": 70,
      "_demo": false
    },
    {
      "doc_num": "2026-10748",
      "doc_type": "AH",
      "filed": "2026-04-30",
      "cat": "probate",
      "cat_label": "Affidavit of Heirship",
      "owner": "THORNTON LORA LEE",
      "grantee": "THORNTON LONNIE BEN DECEASED",
      "amount": null,
      "legal": "Subdivision - Name: SHERWOOD SHORES 1 Lot: 810",
      "prop_address": "1548 LAKE RD",
      "prop_city": "GORDONVILLE",
      "prop_state": "TX",
      "prop_zip": "76245",
      "mail_address": "1548 LAKE RD",
      "mail_city": "GORDONVILLE",
      "mail_state": "TX",
      "mail_zip": "76245",
      "clerk_url": "https://grayson.tx.publicsearch.us/results?department=RP&_docTypes=AH&recordedDateRange=20260429,20260506&searchType=quickSearch&keywordSearch=false&searchOcrText=false",
      "flags": [
        "Probate / estate",
        "New this week"
      ],
      "score": 70,
      "_demo": false
    },
    {
      "doc_num": "2026-10934",
      "doc_type": "AH",
      "filed": "2026-05-01",
      "cat": "probate",
      "cat_label": "Affidavit of Heirship",
      "owner": "HARRELSON MARCY",
      "grantee": "HARRELSON DONALD DECEASED",
      "amount": null,
      "legal": "Subdivision - Name: OAK VIEW ADDN Lot: 5 Block: 20",
      "prop_address": "918 W ACHESON ST",
      "prop_city": "DENISON",
      "prop_state": "TX",
      "prop_zip": "",
      "mail_address": "28 PERSIAN BLVD",
      "mail_city": "POTTSBORO",
      "mail_state": "TX",
      "mail_zip": "75076",
      "clerk_url": "https://grayson.tx.publicsearch.us/results?department=RP&_docTypes=AH&recordedDateRange=20260429,20260506&searchType=quickSearch&keywordSearch=false&searchOcrText=false",
      "flags": [
        "Probate / estate",
        "New this week"
      ],
      "score": 70,
      "_demo": false
    },
    {
      "doc_num": "2026-10964",
      "doc_type": "AH",
      "filed": "2026-05-01",
      "cat": "probate",
      "cat_label": "Affidavit of Heirship",
      "owner": "WALKER JOE",
      "grantee": "BLASSINGAME DEAN WELDON DECEASED",
      "amount": null,
      "legal": "N/A",
      "prop_address": "325 W ARAPAHO TRAIL",
      "prop_city": "SHERMAN",
      "prop_state": "TX",
      "prop_zip": "75092",
      "mail_address": "325 ARAPAHO W",
      "mail_city": "SHERMAN",
      "mail_state": "TX",
      "mail_zip": "75092",
      "clerk_url": "https://grayson.tx.publicsearch.us/results?department=RP&_docTypes=AH&recordedDateRange=20260429,20260506&searchType=quickSearch&keywordSearch=false&searchOcrText=false",
      "flags": [
        "Probate / estate",
        "New this week"
      ],
      "score": 70,
      "_demo": false
    },
    {
      "doc_num": "2026-10954",
      "doc_type": "AH",
      "filed": "2026-05-01",
      "cat": "probate",
      "cat_label": "Affidavit of Heirship",
      "owner": "CHAMPION CHRISTOPHER",
      "grantee": "CHAMPION DACIA ELIZBETH DECEASED",
      "amount": null,
      "legal": "Subdivision - Name: MAGNOLIA PARK ADDN Lot: 22 Block: 6",
      "prop_address": "721 W BROCK ST",
      "prop_city": "DENISON",
      "prop_state": "TX",
      "prop_zip": "",
      "mail_address": "721 W BROCK ST",
      "mail_city": "DENISON",
      "mail_state": "TX",
      "mail_zip": "75020",
      "clerk_url": "https://grayson.tx.publicsearch.us/results?department=RP&_docTypes=AH&recordedDateRange=20260429,20260506&searchType=quickSearch&keywordSearch=false&searchOcrText=false",
      "flags": [
        "Probate / estate",
        "New this week"
      ],
      "score": 70,
      "_demo": false
    },
    {
      "doc_num": "2026-11152",
      "doc_type": "AH",
      "filed": "2026-05-04",
      "cat": "probate",
      "cat_label": "Affidavit of Heirship",
      "owner": "BROOKE JERRY",
      "grantee": "BROOKE LUCY GAY DECEASED",
      "amount": null,
      "legal": "Survey - Name: C MORGAN SUR Survey: 785 Acres: 4.999",
      "prop_address": "1750 ETHEL CEMETERY RD",
      "prop_city": "COLLINSVILLE",
      "prop_state": "TX",
      "prop_zip": "",
      "mail_address": "PO BOX 146",
      "mail_city": "COLLINSVILLE",
      "mail_state": "TX",
      "mail_zip": "76233",
      "clerk_url": "https://grayson.tx.publicsearch.us/results?department=RP&_docTypes=AH&recordedDateRange=20260429,20260506&searchType=quickSearch&keywordSearch=false&searchOcrText=false",
      "flags": [
        "Probate / estate",
        "New this week"
      ],
      "score": 70,
      "_demo": false
    },
    {
      "doc_num": "2026-11102",
      "doc_type": "AH",
      "filed": "2026-05-04",
      "cat": "probate",
      "cat_label": "Affidavit of Heirship",
      "owner": "BROWN MARK",
      "grantee": "BROWN DIANA GAY DECEASED",
      "amount": null,
      "legal": "Survey - Name: C MORGAN SUR Survey: 785 Acres: 4.999",
      "prop_address": "583 COE RD",
      "prop_city": "DENISON",
      "prop_state": "TX",
      "prop_zip": "",
      "mail_address": "583 COE RD",
      "mail_city": "DENISON",
      "mail_state": "TX",
      "mail_zip": "75021",
      "clerk_url": "https://grayson.tx.publicsearch.us/results?department=RP&_docTypes=AH&recordedDateRange=20260429,20260506&searchType=quickSearch&keywordSearch=false&searchOcrText=false",
      "flags": [
        "Probate / estate",
        "New this week"
      ],
      "score": 70,
      "_demo": false
    },
    {
      "doc_num": "2026-11092",
      "doc_type": "AH",
      "filed": "2026-05-04",
      "cat": "probate",
      "cat_label": "Affidavit of Heirship",
      "owner": "REEVES DONNY R",
      "grantee": "REEVES LEIGH HICKS DECEASED",
      "amount": null,
      "legal": "Subdivision - Name: RYAN HILLS ADDN Lot: 20 Block: 2",
      "prop_address": "2100 LUCAS CT",
      "prop_city": "DENISON",
      "prop_state": "TX",
      "prop_zip": "",
      "mail_address": "2100 LUCAS DR",
      "mail_city": "DENISON",
      "mail_state": "TX",
      "mail_zip": "75020",
      "clerk_url": "https://grayson.tx.publicsearch.us/results?department=RP&_docTypes=AH&recordedDateRange=20260429,20260506&searchType=quickSearch&keywordSearch=false&searchOcrText=false",
      "flags": [
        "Probate / estate",
        "New this week"
      ],
      "score": 70,
      "_demo": false
    },
    {
      "doc_num": "2026-10603",
      "doc_type": "AJ",
      "filed": "2026-04-29",
      "cat": "judgment",
      "cat_label": "Abstract of Judgment",
      "owner": "CABADA JUAN",
      "grantee": "CAPITAL ONE NA",
      "amount": null,
      "legal": "$6280.49",
      "prop_address": "212 E BROCKETT",
      "prop_city": "SHERMAN",
      "prop_state": "TX",
      "prop_zip": "75090",
      "mail_address": "212 E BROCKETT ST",
      "mail_city": "SHERMAN",
      "mail_state": "TX",
      "mail_zip": "75090",
      "clerk_url": "https://grayson.tx.publicsearch.us/results?department=RP&_docTypes=AJ&recordedDateRange=20260429,20260506&searchType=quickSearch&keywordSearch=false&searchOcrText=false",
      "flags": [
        "Judgment lien",
        "New this week"
      ],
      "score": 60,
      "_demo": false
    },
    {
      "doc_num": "2026-10852",
      "doc_type": "ALN",
      "filed": "2026-04-30",
      "cat": "lien",
      "cat_label": "HOA Lien",
      "owner": "RICKMAN BRANDON",
      "grantee": "SANFORD PARK HOMEOWNERS ASN INC",
      "amount": null,
      "legal": "Subdivision - Name: SANFORD PARK Lot: 5 Block: F",
      "prop_address": "WILLIAMS WAY",
      "prop_city": "VAN ALSTYNE",
      "prop_state": "TX",
      "prop_zip": "",
      "mail_address": "500 WILLIAMS WAY",
      "mail_city": "VAN ALSTYNE",
      "mail_state": "TX",
      "mail_zip": "75495",
      "clerk_url": "https://grayson.tx.publicsearch.us/results?department=RP&_docTypes=ALN&recordedDateRange=20260429,20260506&searchType=quickSearch&keywordSearch=false&searchOcrText=false",
      "flags": [
        "HOA lien",
        "New this week"
      ],
      "score": 60,
      "_demo": false
    },
    {
      "doc_num": "2026-10780",
      "doc_type": "QCD",
      "filed": "2026-04-30",
      "cat": "other",
      "cat_label": "Quit Claim Deed",
      "owner": "ROBERTSON PAUL",
      "grantee": "ROBERTSON PAUL TRUSTEE",
      "amount": null,
      "legal": "Subdivision - Name: BEL AIR VILLAGE 1 Lot: 43 Block: A",
      "prop_address": "1225 MORGAN DR",
      "prop_city": "SHERMAN",
      "prop_state": "TX",
      "prop_zip": "",
      "mail_address": "1225 MORGAN",
      "mail_city": "SHERMAN",
      "mail_state": "TX",
      "mail_zip": "75090",
      "clerk_url": "https://grayson.tx.publicsearch.us/results?department=RP&_docTypes=QCD&recordedDateRange=20260429,20260506&searchType=quickSearch&keywordSearch=false&searchOcrText=false",
      "flags": [
        "Quit claim deed",
        "New this week"
      ],
      "score": 60,
      "_demo": false
    },
    {
      "doc_num": "2026-10948",
      "doc_type": "DV",
      "filed": "2026-05-01",
      "cat": "other",
      "cat_label": "Divorce",
      "owner": "WOOD DANNY",
      "grantee": "TEAGUE DEBORAH",
      "amount": null,
      "legal": "Subdivision - Name: GEORGETOWN VILLAGE II Lot: 14 Block: D",
      "prop_address": "344 SHERBROOK ST",
      "prop_city": "VAN ALSTYNE",
      "prop_state": "TX",
      "prop_zip": "",
      "mail_address": "PO BOX 2406",
      "mail_city": "ALLEN",
      "mail_state": "TX",
      "mail_zip": "75013",
      "clerk_url": "https://grayson.tx.publicsearch.us/results?department=RP&_docTypes=DV&recordedDateRange=20260429,20260506&searchType=quickSearch&keywordSearch=false&searchOcrText=false",
      "flags": [
        "Divorce",
        "New this week"
      ],
      "score": 60,
      "_demo": false
    },
    {
      "doc_num": "2026-11146",
      "doc_type": "FTL",
      "filed": "2026-05-04",
      "cat": "lien",
      "cat_label": "Federal Tax Lien",
      "owner": "WADE WILLIAM B",
      "grantee": "U S A INTERNAL REVENUE SERVICE",
      "amount": null,
      "legal": "$82754.06",
      "prop_address": "204 N LACKEY ST",
      "prop_city": "TOM BEAN",
      "prop_state": "TX",
      "prop_zip": "",
      "mail_address": "204 N LACKEY ST",
      "mail_city": "TOM BEAN",
      "mail_state": "TX",
      "mail_zip": "75489",
      "clerk_url": "https://grayson.tx.publicsearch.us/results?department=RP&_docTypes=FTL&recordedDateRange=20260429,20260506&searchType=quickSearch&keywordSearch=false&searchOcrText=false",
      "flags": [
        "Tax lien",
        "New this week"
      ],
      "score": 60,
      "_demo": false
    },
    {
      "doc_num": "2026-11080",
      "doc_type": "AJ",
      "filed": "2026-05-04",
      "cat": "judgment",
      "cat_label": "Abstract of Judgment",
      "owner": "PARDEE WILLIAM L",
      "grantee": "CITIBANK NA",
      "amount": null,
      "legal": "$7225.83",
      "prop_address": "148 SHAWNEE TRAIL",
      "prop_city": "POTTSBORO",
      "prop_state": "TX",
      "prop_zip": "",
      "mail_address": "148 SHAWNEE TRL",
      "mail_city": "POTTSBORO",
      "mail_state": "TX",
      "mail_zip": "75076",
      "clerk_url": "https://grayson.tx.publicsearch.us/results?department=RP&_docTypes=AJ&recordedDateRange=20260429,20260506&searchType=quickSearch&keywordSearch=false&searchOcrText=false",
      "flags": [
        "Judgment lien",
        "New this week"
      ],
      "score": 60,
      "_demo": false
    },
    {
      "doc_num": "2026-11088",
      "doc_type": "HL",
      "filed": "2026-05-04",
      "cat": "lien",
      "cat_label": "Hospital Lien",
      "owner": "HERNANDEZ CLAUDIA",
      "grantee": "TEXOMA MEDICAL CENTER",
      "amount": null,
      "legal": "N/A",
      "prop_address": "528 N RICKETTS ST",
      "prop_city": "SHERMAN",
      "prop_state": "TX",
      "prop_zip": "",
      "mail_address": "528 N RICKETTS ST",
      "mail_city": "SHERMAN",
      "mail_state": "TX",
      "mail_zip": "75092",
      "clerk_url": "https://grayson.tx.publicsearch.us/results?department=RP&_docTypes=HL&recordedDateRange=20260429,20260506&searchType=quickSearch&keywordSearch=false&searchOcrText=false",
      "flags": [
        "Hospital lien",
        "New this week"
      ],
      "score": 60,
      "_demo": false
    },
    {
      "doc_num": "2026-11086",
      "doc_type": "HL",
      "filed": "2026-05-04",
      "cat": "lien",
      "cat_label": "Hospital Lien",
      "owner": "SMITH JUSTIN",
      "grantee": "TEXOMA MEDICAL CENTER",
      "amount": null,
      "legal": "N/A",
      "prop_address": "1012 E OWINGS ST",
      "prop_city": "DENISON",
      "prop_state": "TX",
      "prop_zip": "",
      "mail_address": "1012 E OWINGS ST",
      "mail_city": "DENISON",
      "mail_state": "TX",
      "mail_zip": "75021",
      "clerk_url": "https://grayson.tx.publicsearch.us/results?department=RP&_docTypes=HL&recordedDateRange=20260429,20260506&searchType=quickSearch&keywordSearch=false&searchOcrText=false",
      "flags": [
        "Hospital lien",
        "New this week"
      ],
      "score": 60,
      "_demo": false
    },
    {
      "doc_num": "2026-11096",
      "doc_type": "DV",
      "filed": "2026-05-04",
      "cat": "other",
      "cat_label": "Divorce",
      "owner": "PLUMB MARK DENNIS",
      "grantee": "PLUMB PATTI LYNN",
      "amount": null,
      "legal": "Subdivision - Name: GUNTER TOWN CENTER ADDN 1 Lot: 7 Block: D",
      "prop_address": "1164 STONEBRIDGE PASS",
      "prop_city": "GUNTER",
      "prop_state": "TX",
      "prop_zip": "",
      "mail_address": "1164 STONEBRIDGE PASS",
      "mail_city": "GUNTER",
      "mail_state": "TX",
      "mail_zip": "75058",
      "clerk_url": "https://grayson.tx.publicsearch.us/results?department=RP&_docTypes=DV&recordedDateRange=20260429,20260506&searchType=quickSearch&keywordSearch=false&searchOcrText=false",
      "flags": [
        "Divorce",
        "New this week"
      ],
      "score": 60,
      "_demo": false
    },
    {
      "doc_num": "2026-11139",
      "doc_type": "QCD",
      "filed": "2026-05-04",
      "cat": "other",
      "cat_label": "Quit Claim Deed",
      "owner": "FITZGERALD JEANETTE",
      "grantee": "125 HERITAGE LLC",
      "amount": null,
      "legal": "Survey - Name: D YGLESIAS SUR Survey: 1393 Acres: 16.330",
      "prop_address": "125 HERITAGE",
      "prop_city": "GORDONVILLE",
      "prop_state": "TX",
      "prop_zip": "",
      "mail_address": "15632 FM 901",
      "mail_city": "SADLER",
      "mail_state": "TX",
      "mail_zip": "76264",
      "clerk_url": "https://grayson.tx.publicsearch.us/results?department=RP&_docTypes=QCD&recordedDateRange=20260429,20260506&searchType=quickSearch&keywordSearch=false&searchOcrText=false",
      "flags": [
        "Quit claim deed",
        "New this week"
      ],
      "score": 60,
      "_demo": false
    }
  ]
}